{"version": "1", "message": "ERROR: Hidden Testcases server unreachable.", "problem_id": "ads1_m14_a2", "user_id": "khyathimsit", "score": {"sample": {"0": {"execution_time": 0.4995267391204834, "passed": true}, "1": {"execution_time": 0.41878843307495117, "passed": true}, "2": {"execution_time": 0.5389907360076904, "passed": true}, "3": {"execution_time": 0.551560640335083, "passed": true}, "4": {"execution_time": 0.4539775848388672, "passed": true}, "5": {"execution_time": 0.5261585712432861, "passed": true}}}, "check_style_score": "1/1"}